fastenum/__init__.py
fastenum/fastenum.py
fastenum/fastenum.pyi
fastenum/mypy_plugin.py
fastenum/py.typed
fastenum/tests/__init__.py
fastenum/tests/test_benchmark.py
fastenum-1.1.1.dist-info/LICENSE
fastenum-1.1.1.dist-info/METADATA
fastenum-1.1.1.dist-info/WHEEL
fastenum-1.1.1.dist-info/RECORD
