Metadata-Version: 2.1
Name: fastenum
Version: 1.1.1
Summary: Faster drop-in replacement of Python's enum
Home-page: https://gitlab.com/quantlane/libs/fastenum
License: Apache 2.0
Author: Quantlane
Author-email: code@quantlane.com
Requires-Python: >=3.10,<4.0
Classifier: Development Status :: 4 - Beta
Classifier: License :: Other/Proprietary License
Classifier: Programming Language :: Python :: 3
Classifier: Programming Language :: Python :: 3.10
Classifier: Programming Language :: Python :: 3.11
Classifier: Programming Language :: Python :: 3.12
Classifier: Topic :: Software Development :: Libraries
Project-URL: Repository, https://gitlab.com/quantlane/libs/fastenum
